ntv_pandas/__init__.py
ntv_pandas/ntv_pandas.ini
ntv_pandas/ntv_table.ini
ntv_pandas/pandas_accessors.py
ntv_pandas/pandas_ntv_connector.py
ntv_pandas-2.0.1.dist-info/METADATA
ntv_pandas-2.0.1.dist-info/WHEEL
ntv_pandas-2.0.1.dist-info/top_level.txt
ntv_pandas-2.0.1.dist-info/RECORD
