Metadata-Version: 2.1
Name: ntv_pandas
Version: 2.0.1
Summary: NTV-pandas : A tabular analyzer and a semantic, compact and reversible converter
Home-page: https://github.com/loco-philippe/ntv-pandas/blob/main/README.md
Author: Philippe Thomy
Author-email: philippe@loco-labs.io
Keywords: pandas,JSON-NTV,semantic JSON,development,environmental data
Classifier: Development Status :: 5 - Production/Stable
Classifier: Intended Audience :: Developers
Classifier: Topic :: Software Development :: Build Tools
Classifier: License :: OSI Approved :: MIT License
Classifier: Programming Language :: Python :: 3
Requires-Python: >=3.10, <4
Requires-Dist: ntv-numpy
Requires-Dist: tab-analysis
Requires-Dist: tab-dataset
Requires-Dist: json-ntv
Requires-Dist: numpy
Requires-Dist: pandas
Requires-Dist: shapely
